flask_reuploads/__init__.py
flask_reuploads/exceptions.py
flask_reuploads/extensions.py
flask_reuploads/flask_reuploads.py
flask_reuploads/py.typed
flask_reuploads/test_helper.py
Flask_Reuploads-1.0.1.dev0.dist-info/LICENSE
Flask_Reuploads-1.0.1.dev0.dist-info/METADATA
Flask_Reuploads-1.0.1.dev0.dist-info/WHEEL
Flask_Reuploads-1.0.1.dev0.dist-info/top_level.txt
Flask_Reuploads-1.0.1.dev0.dist-info/RECORD
