Metadata-Version: 2.1
Name: Flask-Reuploads
Version: 1.0.1.dev0
Summary: Flexible and efficient upload handling for Flask
Home-page: https://github.com/picklu/flask-reuploads
Author: Matthew "LeafStorm" Frazier
Author-email: leafstormrush@gmail.com
Maintainer: Jürgen Gmach, Subrata Sarker
Maintainer-email: juergen.gmach@googlemail.com, picklumithu@yahoo.com
License: MIT
Project-URL: Source, https://github.com/picklu/flask-reuploads
Project-URL: Issue Tracker, https://github.com/jugmac00/flask-reuploaded/issues
Project-URL: Documentation, https://flask-reuploaded.readthedocs.io/en/latest/
Platform: any
Classifier: Development Status :: 5 - Production/Stable
Classifier: Environment :: Web Environment
Classifier: Intended Audience :: Developers
Classifier: License :: OSI Approved :: MIT License
Classifier: Operating System :: OS Independent
Classifier: Programming Language :: Python
Classifier: Programming Language :: Python :: 3
Classifier: Programming Language :: Python :: 3.7
Classifier: Programming Language :: Python :: 3.8
Classifier: Programming Language :: Python :: 3.9
Classifier: Programming Language :: Python :: 3.10
Classifier: Programming Language :: Python :: 3.11
Classifier: Topic :: Internet :: WWW/HTTP :: Dynamic Content
Classifier: Topic :: Software Development :: Libraries :: Python Modules
Classifier: Framework :: Flask
Requires-Python: >= 3.7
License-File: LICENSE
Requires-Dist: Flask (>=1.0.4)
Provides-Extra: test
Requires-Dist: pytest ; extra == 'test'
Requires-Dist: pytest-cov ; extra == 'test'
